dingtalk_log_handler/__init__.py
dingtalk_log_handler-0.0.7.dist-info/LICENSE
dingtalk_log_handler-0.0.7.dist-info/METADATA
dingtalk_log_handler-0.0.7.dist-info/WHEEL
dingtalk_log_handler-0.0.7.dist-info/top_level.txt
dingtalk_log_handler-0.0.7.dist-info/RECORD
