Metadata-Version: 2.1
Name: dingtalk-log-handler
Version: 0.0.7
Summary: log handler for send message to dingtalk
Author: ruan.lj
Author-email: ruan.lj@foxmail.com
Project-URL: Source, https://github.com/ruanimal/dingtalk-log-handler
Project-URL: Tracker, https://github.com/ruanimal/dingtalk-log-handler/issues
Classifier: Development Status :: 4 - Beta
Classifier: Intended Audience :: Developers
Classifier: Topic :: Software Development :: Libraries
Classifier: Programming Language :: Python :: 3
Classifier: Programming Language :: Python :: 3.5
Classifier: Programming Language :: Python :: 3.6
Classifier: Programming Language :: Python :: 3.7
Classifier: Programming Language :: Python :: 3.8
Requires-Python: >=3.5
License-File: LICENSE
